xmmutablemap/__init__.py
xmmutablemap/_core.py
xmmutablemap/_version.py
xmmutablemap/_version.pyi
xmmutablemap/py.typed
xmmutablemap-0.2.0.dist-info/METADATA
xmmutablemap-0.2.0.dist-info/WHEEL
xmmutablemap-0.2.0.dist-info/licenses/LICENSE
xmmutablemap-0.2.0.dist-info/RECORD
