Metadata-Version: 2.4
Name: xmmutablemap
Version: 0.2.0
Summary: Immutable Map, compatible with JAX & Equinox
Project-URL: Homepage, https://github.com/GalacticDynamics/xmmutablemap
Project-URL: Bug Tracker, https://github.com/GalacticDynamics/xmmutablemap/issues
Project-URL: Discussions, https://github.com/GalacticDynamics/xmmutablemap/discussions
Project-URL: Changelog, https://github.com/GalacticDynamics/xmmutablemap/releases
Author-email: Galactic Dynamics Maintainers <nstarman@users.noreply.github.com>
License: Copyright 2024 Galactic Dynamics Maintainers
License-File: LICENSE
Classifier: Development Status :: 1 - Planning
Classifier: Intended Audience :: Developers
Classifier: Intended Audience :: Science/Research
Classifier: License :: OSI Approved :: MIT License
Classifier: Operating System :: OS Independent
Classifier: Programming Language :: Python
Classifier: Programming Language :: Python :: 3
Classifier: Programming Language :: Python :: 3 :: Only
Classifier: Programming Language :: Python :: 3.10
Classifier: Programming Language :: Python :: 3.11
Classifier: Programming Language :: Python :: 3.12
Classifier: Programming Language :: Python :: 3.13
Classifier: Topic :: Scientific/Engineering
Classifier: Typing :: Typed
Requires-Python: >=3.10
Requires-Dist: jax
Requires-Dist: typing-extensions>=4.8
